setup.py
PyAsciiArt/PyAsciiArt.py
PyAsciiArt/__init__.py
PyAsciiArt/__main__.py
PyAsciiArt.egg-info/PKG-INFO
PyAsciiArt.egg-info/SOURCES.txt
PyAsciiArt.egg-info/dependency_links.txt
PyAsciiArt.egg-info/entry_points.txt
PyAsciiArt.egg-info/requires.txt
PyAsciiArt.egg-info/top_level.txt